{"inshape": [4], "configs_encoder": {"activation": "relu", "latent_dim": 4, "conv_1": {"filter_num": 16, "kernel_size": [4, 4], "stride": 2}, "conv_2": {"filter_num": 16, "kernel_size": [4, 4], "stride": 2}, "conv_3": {"filter_num": 8, "kernel_size": [4, 4], "stride": 2}, "dense_1": {"unit_num": 128}, "dense_2": {"unit_num": 64}, "dense_3": {"unit_num": 32}, "dense_4": {"unit_num": 16}, "dense_5": {"activation": null}}, "config_decoder": {"latent_dim": 4, "activation": "relu", "dense1": {"unit_num": 64}, "dense2": {"unit_num": 128}, "dense3": {"unit_num": 265}, "dense4": {"unit_num": 512}, "dense5": {"unit_num": 1250}}, "config_dense": {"activation": "relu", "layer_1": {"unit_num": 128}, "layer_2": {"unit_num": 128}, "layer_3": {"unit_num": 128}, "layer_4": {"unit_num": 64}, "layer_5": {"unit_num": 1, "activation": null}}, "config_cloudnn": {"activation": "relu", "layer_1": {"unit_num": 64}, "layer_2": {"unit_num": 32}, "layer_3": {"unit_num": 8}, "layer_4": {"unit_num": 1, "activation": null}}}